ossdata/__init__.py
ossdata/cli.py
ossdata/core.py
ossdata/backend/__init__.py
ossdata/backend/nas.py
ossdata/backend/oss.py
ossdata-0.3.5.dist-info/METADATA
ossdata-0.3.5.dist-info/WHEEL
ossdata-0.3.5.dist-info/entry_points.txt
ossdata-0.3.5.dist-info/top_level.txt
ossdata-0.3.5.dist-info/RECORD
