Metadata-Version: 2.4
Name: ossdata
Version: 0.3.5
Summary: Scalable SWE datasets
Author-email: Mouxiang Chen <cmx_1007@foxmail.com>
License: MIT
Classifier: Programming Language :: Python :: 3
Classifier: License :: OSI Approved :: MIT License
Classifier: Operating System :: OS Independent
Requires-Python: >=3.8
Requires-Dist: datasets
Requires-Dist: tqdm
Requires-Dist: alibabacloud-oss-v2
